{
  "experiment_name": "kmeans_tfidf",
  "seed": 854,
  "n_documents": 11003,
  "n_features": 150,
  "n_clusters_found": 20,
  "metrics": {
    "silhouette": 0.049480829387903214,
    "davies_bouldin": 4.066225830056154,
    "calinski_harabasz": 98.46496670441462
  },
  "objective": 8723.8662109375,
  "cluster_sizes": {
    "0": 79,
    "1": 237,
    "2": 259,
    "3": 312,
    "4": 657,
    "5": 124,
    "6": 549,
    "7": 365,
    "8": 210,
    "9": 639,
    "10": 863,
    "11": 263,
    "12": 402,
    "13": 511,
    "14": 1797,
    "15": 781,
    "16": 265,
    "17": 443,
    "18": 211,
    "19": 2036
  },
  "selected_metric": "silhouette",
  "interpretation": {
    "cluster_terms": {
      "0": [
        [
          "geb",
          0.1561315953731537
        ],
        [
          "gordon",
          0.15610601007938385
        ],
        [
          "gordon banks",
          0.15483257174491882
        ],
        [
          "pitt edu",
          0.15483257174491882
        ],
        [
          "shameful",
          0.15234696865081787
        ],
        [
          "pitt",
          0.15155942738056183
        ],
        [
          "dsl pitt",
          0.14854538440704346
        ],
        [
          "intellect geb",
          0.14854538440704346
        ],
        [
          "cadre dsl",
          0.14854538440704346
        ],
        [
          "edu shameful",
          0.14854538440704346
        ]
      ],
      "1": [
        [
          "right",
          0.16761469841003418
        ],
        [
          "left",
          0.032042328268289566
        ],
        [
          "people",
          0.023704424500465393
        ],
        [
          "just",
          0.02125559374690056
        ],
        [
          "like",
          0.01998060569167137
        ],
        [
          "know",
          0.01812158338725567
        ],
        [
          "way",
          0.016612734645605087
        ],
        [
          "think",
          0.014948945492506027
        ],
        [
          "want",
          0.014240158721804619
        ],
        [
          "course",
          0.013696666806936264
        ]
      ],
      "2": [
        [
          "com",
          0.20986413955688477
        ],
        [
          "netcom com",
          0.026359159499406815
        ],
        [
          "netcom",
          0.026276135817170143
        ],
        [
          "irq",
          0.025972913950681686
        ],
        [
          "internet",
          0.019341371953487396
        ],
        [
          "tek",
          0.018366575241088867
        ],
        [
          "apr",
          0.0172513909637928
        ],
        [
          "dave",
          0.017232362180948257
        ],
        [
          "corp",
          0.017020659521222115
        ],
        [
          "bob",
          0.016329746693372726
        ]
      ],
      "3": [
        [
          "key",
          0.14866574108600616
        ],
        [
          "clipper",
          0.08297079056501389
        ],
        [
          "encryption",
          0.08168363571166992
        ],
        [
          "chip",
          0.07759939879179001
        ],
        [
          "keys",
          0.06417340785264969
        ],
        [
          "escrow",
          0.04470250383019447
        ],
        [
          "government",
          0.0403057262301445
        ],
        [
          "nsa",
          0.0399429015815258
        ],
        [
          "clipper chip",
          0.03541453182697296
        ],
        [
          "algorithm",
          0.03430650010704994
        ]
      ],
      "4": [
        [
          "drive",
          0.09361888468265533
        ],
        [
          "card",
          0.06855516135692596
        ],
        [
          "mb",
          0.054004669189453125
        ],
        [
          "scsi",
          0.05060678347945213
        ],
        [
          "bus",
          0.03456271067261696
        ],
        [
          "disk",
          0.03386688977479935
        ],
        [
          "controller",
          0.03226868063211441
        ],
        [
          "drives",
          0.03047853335738182
        ],
        [
          "video",
          0.029684072360396385
        ],
        [
          "mhz",
          0.029184672981500626
        ]
      ],
      "5": [
        [
          "armenian",
          0.15541082620620728
        ],
        [
          "armenians",
          0.13804090023040771
        ],
        [
          "turkish",
          0.1292862445116043
        ],
        [
          "turkey",
          0.07472426444292068
        ],
        [
          "turks",
          0.06878329813480377
        ],
        [
          "armenia",
          0.06854995340108871
        ],
        [
          "greek",
          0.05815964192152023
        ],
        [
          "genocide",
          0.05811723321676254
        ],
        [
          "serdar",
          0.05088036507368088
        ],
        [
          "people",
          0.05004188045859337
        ]
      ],
      "6": [
        [
          "just",
          0.1422857940196991
        ],
        [
          "like",
          0.02572646737098694
        ],
        [
          "know",
          0.019232522696256638
        ],
        [
          "think",
          0.018970897421240807
        ],
        [
          "people",
          0.01837857812643051
        ],
        [
          "ll",
          0.01420264970511198
        ],
        [
          "ve",
          0.013876805081963539
        ],
        [
          "good",
          0.013632710091769695
        ],
        [
          "want",
          0.01339650247246027
        ],
        [
          "wondering",
          0.013376380316913128
        ]
      ],
      "7": [
        [
          "sale",
          0.09845633059740067
        ],
        [
          "offer",
          0.06711483746767044
        ],
        [
          "shipping",
          0.06482591480016708
        ],
        [
          "condition",
          0.05280829593539238
        ],
        [
          "price",
          0.04212792217731476
        ],
        [
          "asking",
          0.040598295629024506
        ],
        [
          "new",
          0.03717891499400139
        ],
        [
          "best offer",
          0.03449372202157974
        ],
        [
          "sell",
          0.03322562202811241
        ],
        [
          "excellent",
          0.02925175614655018
        ]
      ],
      "8": [
        [
          "bike",
          0.1937987506389618
        ],
        [
          "bikes",
          0.05157672241330147
        ],
        [
          "ride",
          0.046307120472192764
        ],
        [
          "dod",
          0.03962232917547226
        ],
        [
          "helmet",
          0.0388946607708931
        ],
        [
          "honda",
          0.037375058978796005
        ],
        [
          "riding",
          0.034015171229839325
        ],
        [
          "motorcycle",
          0.029895827174186707
        ],
        [
          "dog",
          0.026297029107809067
        ],
        [
          "like",
          0.024589702486991882
        ]
      ],
      "9": [
        [
          "government",
          0.0510663203895092
        ],
        [
          "gun",
          0.05080382898449898
        ],
        [
          "people",
          0.04014278203248978
        ],
        [
          "law",
          0.03648648411035538
        ],
        [
          "guns",
          0.028690358623862267
        ],
        [
          "state",
          0.024603772908449173
        ],
        [
          "rights",
          0.024152440950274467
        ],
        [
          "crime",
          0.02254733256995678
        ],
        [
          "laws",
          0.021970881149172783
        ],
        [
          "police",
          0.02007448486983776
        ]
      ],
      "10": [
        [
          "windows",
          0.07988540083169937
        ],
        [
          "file",
          0.05434300750494003
        ],
        [
          "window",
          0.04620944336056709
        ],
        [
          "dos",
          0.04025740921497345
        ],
        [
          "files",
          0.038210853934288025
        ],
        [
          "program",
          0.03544008731842041
        ],
        [
          "using",
          0.026882439851760864
        ],
        [
          "problem",
          0.026286756619811058
        ],
        [
          "server",
          0.024522429332137108
        ],
        [
          "running",
          0.024380384013056755
        ]
      ],
      "11": [
        [
          "space",
          0.16553141176700592
        ],
        [
          "nasa",
          0.06731390953063965
        ],
        [
          "orbit",
          0.04128085449337959
        ],
        [
          "moon",
          0.035693295300006866
        ],
        [
          "launch",
          0.035440560430288315
        ],
        [
          "earth",
          0.034834928810596466
        ],
        [
          "lunar",
          0.0336112380027771
        ],
        [
          "shuttle",
          0.03213489055633545
        ],
        [
          "satellite",
          0.024905646219849586
        ],
        [
          "data",
          0.02353079803287983
        ]
      ],
      "12": [
        [
          "does",
          0.1473451554775238
        ],
        [
          "know",
          0.0878128856420517
        ],
        [
          "does know",
          0.07895027846097946
        ],
        [
          "thanks",
          0.043156035244464874
        ],
        [
          "does anybody",
          0.03215200453996658
        ],
        [
          "anybody",
          0.029090458527207375
        ],
        [
          "anybody know",
          0.023480011150240898
        ],
        [
          "like",
          0.021679747849702835
        ],
        [
          "info",
          0.017196349799633026
        ],
        [
          "help",
          0.015497461892664433
        ]
      ],
      "13": [
        [
          "god",
          0.18327727913856506
        ],
        [
          "jesus",
          0.07524596899747849
        ],
        [
          "bible",
          0.045002955943346024
        ],
        [
          "faith",
          0.039787545800209045
        ],
        [
          "christ",
          0.03831525892019272
        ],
        [
          "christians",
          0.037840887904167175
        ],
        [
          "believe",
          0.037626963108778
        ],
        [
          "people",
          0.037236932665109634
        ],
        [
          "christian",
          0.036291442811489105
        ],
        [
          "church",
          0.03053404949605465
        ]
      ],
      "14": [
        [
          "thanks",
          0.033273372799158096
        ],
        [
          "edu",
          0.024952633306384087
        ],
        [
          "mail",
          0.023699622601270676
        ],
        [
          "looking",
          0.0174696147441864
        ],
        [
          "information",
          0.014668361283838749
        ],
        [
          "email",
          0.013894457370042801
        ],
        [
          "address",
          0.013422837480902672
        ],
        [
          "hi",
          0.013220150023698807
        ],
        [
          "advance",
          0.013144678436219692
        ],
        [
          "need",
          0.01296356413513422
        ]
      ],
      "15": [
        [
          "game",
          0.06260884553194046
        ],
        [
          "team",
          0.061370350420475006
        ],
        [
          "year",
          0.04476428031921387
        ],
        [
          "games",
          0.03970230743288994
        ],
        [
          "players",
          0.03736897557973862
        ],
        [
          "season",
          0.03384255990386009
        ],
        [
          "hockey",
          0.030601846054196358
        ],
        [
          "play",
          0.030060898512601852
        ],
        [
          "league",
          0.024064727127552032
        ],
        [
          "teams",
          0.02383628487586975
        ]
      ],
      "16": [
        [
          "car",
          0.22184984385967255
        ],
        [
          "cars",
          0.0460616834461689
        ],
        [
          "engine",
          0.036165401339530945
        ],
        [
          "dealer",
          0.027426263317465782
        ],
        [
          "like",
          0.02551870606839657
        ],
        [
          "good",
          0.023365221917629242
        ],
        [
          "ford",
          0.021236028522253036
        ],
        [
          "miles",
          0.020004842430353165
        ],
        [
          "driving",
          0.019069887697696686
        ],
        [
          "new",
          0.018172189593315125
        ]
      ],
      "17": [
        [
          "use",
          0.1377449929714203
        ],
        [
          "using",
          0.022579312324523926
        ],
        [
          "like",
          0.020193547010421753
        ],
        [
          "used",
          0.01733662560582161
        ],
        [
          "ve",
          0.016477296128869057
        ],
        [
          "good",
          0.016031641513109207
        ],
        [
          "need",
          0.015552775003015995
        ],
        [
          "just",
          0.014437972567975521
        ],
        [
          "know",
          0.013792417012155056
        ],
        [
          "want",
          0.013013315387070179
        ]
      ],
      "18": [
        [
          "israel",
          0.1775922328233719
        ],
        [
          "israeli",
          0.10440301895141602
        ],
        [
          "jews",
          0.08424145728349686
        ],
        [
          "arab",
          0.06620418280363083
        ],
        [
          "arabs",
          0.048362959176301956
        ],
        [
          "jewish",
          0.038676027208566666
        ],
        [
          "israelis",
          0.03732284530997276
        ],
        [
          "peace",
          0.03719766065478325
        ],
        [
          "palestinian",
          0.035388655960559845
        ],
        [
          "lebanon",
          0.03203434869647026
        ]
      ],
      "19": [
        [
          "think",
          0.026751646772027016
        ],
        [
          "people",
          0.025917161256074905
        ],
        [
          "like",
          0.021639905869960785
        ],
        [
          "did",
          0.01836761087179184
        ],
        [
          "time",
          0.017972948029637337
        ],
        [
          "know",
          0.016379594802856445
        ],
        [
          "say",
          0.015220950357615948
        ],
        [
          "really",
          0.013761511072516441
        ],
        [
          "said",
          0.013523298315703869
        ],
        [
          "good",
          0.013209963217377663
        ]
      ]
    },
    "metadata": {
      "interpreter": "tfidf",
      "top_n_terms": 10,
      "uses_original_features": true,
      "uses_original_feature_names": true,
      "labels_true_provided": false
    }
  }
}